MANIFEST.in
README.rst
requirements.txt
setup.cfg
setup.py
Morrison/__init__.py
Morrison/airline.py
Morrison/bot.py
Morrison/buttons.py
Morrison/utils.py
Morrison.egg-info/PKG-INFO
Morrison.egg-info/SOURCES.txt
Morrison.egg-info/dependency_links.txt
Morrison.egg-info/requires.txt
Morrison.egg-info/top_level.txt
morrison/__init__.py
morrison/airline.py
morrison/bot.py
morrison/buttons.py
morrison/utils.py