Metadata-Version: 1.1
Name: Morrison
Version: 0.9.51
Summary: A clean Python Wrapper for Facebook Messenger Platform
Home-page: https://github.com/thecolumbialion/Morrison
Author: The Columbia Lion
Author-email: operations@columbialion.com
License: MIT
Download-URL: https://github.com/thecolumbialion/Morrison/archive/0.9.1.tar.gz
Keywords: facebook messenger,python,wrapper,bot,messenger bot,python wrapper,chatbots
Platform: UNKNOWN
